README.txt
setup.py
collective/__init__.py
collective.piwik.core.egg-info/PKG-INFO
collective.piwik.core.egg-info/SOURCES.txt
collective.piwik.core.egg-info/dependency_links.txt
collective.piwik.core.egg-info/entry_points.txt
collective.piwik.core.egg-info/namespace_packages.txt
collective.piwik.core.egg-info/not-zip-safe
collective.piwik.core.egg-info/requires.txt
collective.piwik.core.egg-info/top_level.txt
collective/piwik/__init__.py
collective/piwik/core/__init__.py
collective/piwik/core/configure.zcml
collective/piwik/core/controlpanel.py
collective/piwik/core/interfaces.py
collective/piwik/core/subscribers.py
collective/piwik/core/tests.py
collective/piwik/core/version.txt
collective/piwik/core/browser/__init__.py
collective/piwik/core/browser/configure.zcml
collective/piwik/core/browser/interfaces.py
collective/piwik/core/browser/images/piwik_logo.ico
collective/piwik/core/profiles/default/browserlayer.xml
collective/piwik/core/profiles/default/controlpanel.xml
collective/piwik/core/profiles/default/metadata.xml
collective/piwik/core/profiles/default/registry.xml
docs/HISTORY.txt
docs/INSTALL.txt
docs/LICENSE.GPL
docs/LICENSE.txt