Metadata-Version: 1.0
Name: collective.piwik.core
Version: 0.4
Summary: Analytics support for pages using Piwik (core package)
Home-page: https://github.com/plumi/collective.piwik.core
Author: unweb.me
Author-email: we@unweb.me
License: GPL
Keywords: analytics piwik plone
Platform: UNKNOWN
Classifier: Framework :: Plone
Classifier: Programming Language :: Python
